app/__init__.py
app/__main__.py
app/card.py
app/main.py
app/url_shortener.py
corefinder-1.2.9.dist-info/licenses/LICENSE
corefinder-1.2.9.dist-info/METADATA
corefinder-1.2.9.dist-info/WHEEL
corefinder-1.2.9.dist-info/entry_points.txt
corefinder-1.2.9.dist-info/top_level.txt
corefinder-1.2.9.dist-info/RECORD
