Metadata-Version: 2.4
Name: corefinder
Version: 1.2.9
Summary: A sophisticated Python CLI application that generates a beautiful ASCII art digital business card with interactive URL shortening and clickable hyperlinks
Author-email: Soumyajit Basu <soumyajit.basu62@gmail.com>
License-Expression: MIT
Project-URL: Homepage, https://github.com/Corefinder89/corefinder
Project-URL: Repository, https://github.com/Corefinder89/corefinder
Project-URL: Issues, https://github.com/Corefinder89/corefinder/issues
Project-URL: Changelog, https://github.com/Corefinder89/corefinder/blob/master/CHANGELOG.md
Project-URL: Documentation, https://github.com/Corefinder89/corefinder/blob/master/README.md
Keywords: cli,business-card,ascii-art,url-shortener,terminal,hyperlinks,digital-card
Classifier: Development Status :: 5 - Production/Stable
Classifier: Intended Audience :: Developers
Classifier: Operating System :: OS Independent
Classifier: Programming Language :: Python :: 3.8
Classifier: Programming Language :: Python :: 3.9
Classifier: Programming Language :: Python :: 3.10
Classifier: Programming Language :: Python :: 3.11
Classifier: Programming Language :: Python :: 3.12
Classifier: Topic :: Software Development :: Libraries :: Python Modules
Classifier: Topic :: Utilities
Classifier: Topic :: System :: System Shells
Classifier: Environment :: Console
Requires-Python: >=3.8
License-File: LICENSE
Dynamic: license-file
